curse_api/__init__.py
curse_api/abc.py
curse_api/api.py
curse_api/categories.py
curse_api/clients/aiohttp.py
curse_api/clients/httpx.py
curse_api/enums.py
curse_api/errors.py
curse_api/ext/__init__.py
curse_api/ext/manifest.py
curse_api/models.py
curse_api-3.1.2.dist-info/METADATA
curse_api-3.1.2.dist-info/WHEEL
curse_api-3.1.2.dist-info/RECORD
