Metadata-Version: 2.1
Name: curse-api
Version: 3.1.2
Summary: A simple curseforge api wrapper
Home-page: https://github.com/Stinky-c/curse-api
License: MIT
Keywords: curseforge,api wrapper
Author: Stinky-c
Author-email: 60587749+Stinky-c@users.noreply.github.com
Requires-Python: >=3.7,<4.0
Classifier: Development Status :: 4 - Beta
Classifier: License :: OSI Approved :: MIT License
Classifier: Programming Language :: Python :: 3
Classifier: Programming Language :: Python :: 3.7
Classifier: Programming Language :: Python :: 3.8
Classifier: Programming Language :: Python :: 3.9
Classifier: Programming Language :: Python :: 3.10
Classifier: Programming Language :: Python :: 3.11
Classifier: Programming Language :: Python :: 3.10
Classifier: Programming Language :: Python :: 3.8
Classifier: Programming Language :: Python :: 3.9
Provides-Extra: aiohttp
Provides-Extra: httpx
Provides-Extra: quick
Requires-Dist: aiohttp (>=3.8.4,<4.0.0) ; extra == "aiohttp"
Requires-Dist: httpx (>=0.23.1,<0.24.0) ; extra == "quick" or extra == "httpx"
Requires-Dist: pydantic (>=1.10.4,<2.0.0)
Project-URL: Repository, https://github.com/Stinky-c/curse-api
